pkg_18604/__init__.py
pkg_18604/__main__.py
pkg_18604/run.py
pkg_18604-1.1.20.dist-info/licenses/LICENSE
pkg_18604-1.1.20.dist-info/METADATA
pkg_18604-1.1.20.dist-info/WHEEL
pkg_18604-1.1.20.dist-info/entry_points.txt
pkg_18604-1.1.20.dist-info/top_level.txt
pkg_18604-1.1.20.dist-info/RECORD
