Metadata-Version: 2.4
Name: pkg-18604
Version: 1.1.20
Author-email: developers <developers@tagdots.com>
Project-URL: Changelog, https://github.com/tagdots/setup-badges/blob/main/CHANGELOG.md
Project-URL: Documentation, https://github.com/tagdots/setup-badges/blob/main/README.md
Project-URL: Homepage, https://github.com/tagdots
Project-URL: Issues, https://github.com/tagdots/setup-badges/issues
Project-URL: Repository, https://github.com/tagdots/setup-badges
Classifier: Intended Audience :: Developers
Classifier: Programming Language :: Python :: 3 :: Only
Classifier: Programming Language :: Python :: 3.12
Classifier: Programming Language :: Python :: 3.13
Classifier: Topic :: Software Development :: Build Tools
Requires-Python: >=3.12.10
License-File: LICENSE
Requires-Dist: click==8.2.1
Requires-Dist: click-option-group==0.5.7
Requires-Dist: gitpython==3.1.44
Requires-Dist: setuptools==80.9.0
Requires-Dist: virtualenv==20.31.2
Provides-Extra: test
Requires-Dist: build; extra == "test"
Requires-Dist: commitizen; extra == "test"
Requires-Dist: coverage; extra == "test"
Requires-Dist: flake8; extra == "test"
Requires-Dist: isort; extra == "test"
Requires-Dist: pre-commit; extra == "test"
Requires-Dist: pyscan-rs; extra == "test"
Requires-Dist: pytest; extra == "test"
Requires-Dist: pytest-cov; extra == "test"
Requires-Dist: twine; extra == "test"
Dynamic: license-file
